cornifer/__init__.py
cornifer/blocks.py
cornifer/errors.py
cornifer/example.py
cornifer/file_metadata.py
cornifer/info.py
cornifer/register_file_structure.py
cornifer/register_loader.py
cornifer/registers.py
cornifer/version.py
cornifer/utilities/__init__.py
cornifer/utilities/lmdb.py
Cornifer-0.1.dist-info/LICENSE
Cornifer-0.1.dist-info/METADATA
Cornifer-0.1.dist-info/WHEEL
Cornifer-0.1.dist-info/top_level.txt
Cornifer-0.1.dist-info/RECORD
